{"1":{"class_type":"CheckpointLoaderSimple","inputs":{"ckpt_name":"Juggernaut-XL_v9_RunDiffusionPhoto_v2.safetensors"}},"2":{"class_type":"CLIPTextEncode","inputs":{"text":"real photo, 25yo asian woman, white linen blouse, denim jeans, walking on a tokyo crosswalk at golden hour, neon signs, motion blur of passing cars, shallow depth of field, 50mm f1.8, kodak portra 400 film grain, cinematic, (photorealistic:1.2), (raw photo:1.2), film grain, real skin texture","clip":["1",1]}},"3":{"class_type":"CLIPTextEncode","inputs":{"text":"cartoon, anime, illustration, 3d render, plastic skin, oversmooth, deformed hands, blurry, low quality, bad anatomy, watermark, text","clip":["1",1]}},"4":{"class_type":"LoadImage","inputs":{"image":"ref_w1.png"}},"5":{"class_type":"CannyEdgePreprocessor","inputs":{"image":["4",0],"low_threshold":100,"high_threshold":200,"resolution":1024}},"6":{"class_type":"ControlNetLoader","inputs":{"control_net_name":"controlnet-union-sdxl-promax.safetensors"}},"7":{"class_type":"SetUnionControlNetType","inputs":{"control_net":["6",0],"type":"canny/lineart/anime_lineart/mlsd"}},"8":{"class_type":"ControlNetApplyAdvanced","inputs":{"positive":["2",0],"negative":["3",0],"control_net":["7",0],"image":["5",0],"strength":0.7,"start_percent":0,"end_percent":0.8}},"9":{"class_type":"EmptyLatentImage","inputs":{"width":1024,"height":1024,"batch_size":1}},"10":{"class_type":"KSampler","inputs":{"model":["1",0],"positive":["8",0],"negative":["8",1],"latent_image":["9",0],"seed":7,"steps":30,"cfg":5,"sampler_name":"dpmpp_2m","scheduler":"karras","denoise":1}},"11":{"class_type":"VAEDecode","inputs":{"samples":["10",0],"vae":["1",2]}},"12":{"class_type":"SaveImage","inputs":{"images":["11",0],"filename_prefix":"realistic_w3"}}}